quickkeys/QuickOTP.py
quickkeys/QuickPass.py
quickkeys/__init__.py
quickkeys-0.0.2.dist-info/METADATA
quickkeys-0.0.2.dist-info/WHEEL
quickkeys-0.0.2.dist-info/top_level.txt
quickkeys-0.0.2.dist-info/RECORD
